retry_later/__init__.py
retry_later/lib.py
retry_later/types.py
retry_later-0.0.5.dist-info/LICENSE
retry_later-0.0.5.dist-info/METADATA
retry_later-0.0.5.dist-info/WHEEL
retry_later-0.0.5.dist-info/top_level.txt
retry_later-0.0.5.dist-info/RECORD
