Metadata-Version: 2.1
Name: retry_later
Version: 0.0.5
Summary: Retry your functions later, asynchronously
Author-email: Krishnasis Mandal <krishnasis.mandal@prestatech.com>
Maintainer-email: Krishnasis Mandal <krishnasis.mandal@prestatech.com>
License: MIT License
Keywords: utils,retry,python
Classifier: License :: OSI Approved :: MIT License
Classifier: Programming Language :: Python :: 3.11
Classifier: Programming Language :: Python :: 3.10
Classifier: Programming Language :: Python :: 3.9
Requires-Python: >=3.9
License-File: LICENSE
Provides-Extra: dev
Requires-Dist: pytest ; extra == 'dev'
Requires-Dist: pytest-cov ; extra == 'dev'
Requires-Dist: pytest-xdist ; extra == 'dev'
Requires-Dist: pytest-asyncio ; extra == 'dev'
Requires-Dist: pylint ; extra == 'dev'
Requires-Dist: mypy ; extra == 'dev'
Requires-Dist: typing-extensions ; extra == 'dev'
Requires-Dist: pre-commit ; extra == 'dev'
Requires-Dist: ruff ; extra == 'dev'
